<?xml version="1.0" encoding="utf-8"?>
<!DOCTYPE hibernate-mapping PUBLIC "-//Hibernate/Hibernate Mapping DTD 3.0//EN"
"http://hibernate.sourceforge.net/hibernate-mapping-3.0.dtd">
<!-- 
    Mapping file autogenerated by MyEclipse Persistence Tools
-->
<hibernate-mapping>
    <class name="com.psit.struts.entity.ERPOrdProductOutDetail" table="erp_order_product_out_detail" >
        <id name="id" type="java.lang.String">
            <column name="id" />
            <generator class="assigned" />
        </id>
        <property name="podCode" type="java.lang.String">
            <column name="pod_code" length="300" />
        </property>
        <property name="podStatus" type="java.lang.String">
            <column name="pod_status" length="50" />
        </property>
        <property name="podDate" type="java.lang.String">
            <column name="pod_date" length="50" />
        </property>
        <property name="podSender" type="java.lang.String">
            <column name="pod_sender" length="50" />
        </property>
            <property name="podSendWay" type="java.lang.String">
            <column name="pod_send_way" length="50" />
        </property> 
       <property name="remark" type="java.lang.String">
            <column name="remark" length="100" />
        </property>  
        <property name="total" type="java.lang.Double">
            <column name="total" length="50" />
        </property>    
        <many-to-one name="erpOrdProductOut" class="com.psit.struts.entity.ERPOrdProductOut" fetch="select" not-null="false">
        	<column name="po_id" />
        </many-to-one>
        <many-to-one name="erpSalOrder" class="com.psit.struts.entity.ERPSalOrder" fetch="select" not-null="false">
        	<column name="order_id" />
        </many-to-one>
        <property name="person" type="java.lang.String">
            <column name="person" length="300" />
        </property>
        <property name="address" type="java.lang.String">
            <column name="address" length="300" />
        </property>
        <property name="phone" type="java.lang.String">
            <column name="phone" length="50" />
        </property>
        <property name="zipCode" type="java.lang.String">
            <column name="zip_code" length="50" />
        </property>
       <!-- <one-to-one name="erpOrderCus" class="com.psit.struts.entity.ERPOrderCus" property-ref="erpSalOrder"/> --> 
    </class>
</hibernate-mapping>
